{
  "id": "atom_pest_c",
  "schemaVersion": 1,
  "name": "PEST-C 分析",
  "nameEn": "PEST-C Analysis",
  "frameworkId": "product-innovation-24",
  "cellId": 1,
  "tags": [
    "PEST",
    "宏观分析",
    "趋势扫描",
    "外部环境"
  ],
  "parentAtomId": "atom_macro_scanning",
  "relationType": "child",
  "coreIdea": "把外部环境拆成 政治 / 经济 / 社会 / 技术 / 文化 五个独立透镜分别扫描，再合成。比起拍脑袋的「行业洞察」，PEST-C 强迫你看到自己原本盲区的那一面——产品人最容易低估的往往是政治和文化。",
  "whenToUse": "进入新市场/新地区 · 战略年会准备 · 监管敏感行业（金融/医疗/教育）立项 · 出海前的目标国调研 · 投资委员会答辩材料",
  "keySteps": [
    "1. 锁定分析对象：哪个产品 / 哪个市场 / 哪个时间窗",
    "2. 五个维度各列 5-8 条初始假设（先求广度再求深度）",
    "3. 为每条假设找 1-2 个证据（数据 / 政策原文 / 新闻 / 报告）",
    "4. 评估每条的「冲击力 × 不确定性」，画 2×2 矩阵",
    "5. 高冲击 + 高不确定的进入「监控清单」；高冲击 + 低不确定的进入「行动清单」",
    "6. 把行动清单串成不超过 3 条战略含义"
  ],
  "aiSkillPrompt": "你是一位资深 PEST-C 分析师，擅长将零散的宏观信息转化为产品决策依据。我将提供一个产品/市场场景，请你按以下流程执行：\n\n## 输入\n{请在此处填入：产品名 + 目标市场/地区 + 当前阶段}\n\n## 任务\n1. 在 P / E / S / T / C 五个维度，每个维度列 4-6 条与该产品强相关的外部因素（不要写通用废话，必须紧扣该产品）\n2. 为每条因素给出：\n   - 当前状态（一句话事实）\n   - 未来 18 个月的演化方向（上升/平稳/下降）\n   - 对产品的具体影响（产品的哪个模块/指标会被影响）\n   - 应对动作（产品侧能做什么，禁止说「持续关注」）\n3. 在五个维度结束后，识别 2 条跨维度的复合趋势（例如 政策×技术 联动）\n4. 给出一个「高冲击 × 高不确定」象限内的 Top 3 风险\n\n## 输出格式\n按 5 个维度分章节，每个章节用 Markdown 表格：因素 | 现状 | 趋势 | 产品影响 | 应对动作。最后单独章节输出「复合趋势」和「Top 3 风险」。\n\n## 约束\n- 每条因素必须能被一个 PM 立刻理解，不允许咨询行话\n- 禁止编造数据和政策名称，不确定就标 (需核实)\n- 文化（C）维度必须包含目标用户的代际/亚文化变化，不能只写「消费升级」\n- 全文 800-1500 字",
  "example": {
    "title": "经典案例 · TikTok 进入印度的 PEST-C",
    "content": "字节跳动 2017 年进入印度时的 PEST-C 显示：技术维度（4G 流量价格暴跌至 $0.17/GB）和文化维度（多语言、低识字率催生视频消费）极为利好；但政治维度的「数据本地化 + 中印关系紧张」被低估为低风险——这恰恰是 2020 年被禁的根本原因。事后看，PEST-C 的政治列其实早已闪红灯。"
  },
  "bookmarks": [],
  "stats": {
    "usedInProjects": [],
    "useCount": 0
  },
  "createdAt": "2026-04-07T00:00:00Z",
  "updatedAt": "2026-04-08T10:59:53.224Z",
  "kind": "methodology"
}
